{
  "kind": "collectionType",
  "collectionName": "bills",
  "info": {
    "singularName": "bill",
    "pluralName": "bills",
    "displayName": "Bill",
    "description": ""
  },
  "options": {
    "draftAndPublish": false
  },
  "pluginOptions": {},
  "attributes": {
    "name": {
      "type": "string",
      "required": true
    },
    "note": {
      "type": "string"
    },
    "items": {
      "displayName": "items",
      "type": "component",
      "repeatable": true,
      "component": "common.items"
    },
    "status": {
      "type": "enumeration",
      "enum": [
        "pending",
        "payed",
        "completed"
      ],
      "default": "pending"
    }
  }
}
